[
  {
    "id": "hyundai-grandeur-2025-25",
    "manufacturer": "현대",
    "model": "그랜저",
    "year": 2025,
    "variant": "2.5 가솔린",
    "category": "세단",
    "specs": {
      "engine": "스마트스트림 가솔린 2.5",
      "horsepower": 198,
      "torque": 255,
      "transmission": "8단 자동",
      "drivetrain": "전륜구동",
      "fuelEfficiency": "11.7 km/L",
      "dimensions": {
        "length": 5035,
        "width": 1880,
        "height": 1460,
        "wheelbase": 2895,
        "groundClearance": 150,
        "curbWeight": 1620,
        "trunkCapacity": 480,
        "fuelTankCapacity": 60
      },
      "engineDetails": {
        "type": "직렬 4기통 자연흡기 가솔린",
        "displacement": 2497,
        "cylinders": 4,
        "valves": 16,
        "compressionRatio": "13.0:1",
        "bore": 88,
        "stroke": 102.4
      },
      "performance": {
        "acceleration": 9.2,
        "topSpeed": 210,
        "combinedFuelEconomy": "11.7 km/L",
        "cityFuelEconomy": "10.2 km/L",
        "highwayFuelEconomy": "14.0 km/L"
      },
      "suspension": {
        "front": "맥퍼슨 스트럿",
        "rear": "멀티링크"
      },
      "brakes": {
        "front": "벤틸레이티드 디스크",
        "rear": "디스크",
        "frontDiscSize": 320,
        "rearDiscSize": 300
      },
      "tires": {
        "front": "245/45R19",
        "rear": "245/45R19",
        "wheelSize": "19인치 알로이"
      },
      "safety": {
        "airbags": 10,
        "adasFeatures": [
          "전방 충돌방지 보조",
          "차로 이탈방지 보조",
          "차로 유지 보조",
          "하이빔 보조",
          "후측방 충돌방지 보조",
          "안전 하차 보조",
          "원격 스마트 주차 보조",
          "고속도로 주행 보조 2"
        ]
      },
      "comfort": {
        "seats": 5,
        "seatMaterial": "천연가죽",
        "sunroof": "파노라믹 썬루프"
      }
    },
    "modelInfo": {
      "introduction": "1986년, 대한민국 자동차 역사에 새로운 장이 열렸다. 현대 그랜저. 국산차로는 최초로 V6 엔진을 품은 이 세단은 단순한 이동수단을 넘어 '성공'이라는 단어의 동의어가 되었다. 거리 위의 그랜저는 곧 누군가의 꿈이었고, 그 꿈을 향해 달려온 시간의 증거였다.\n\n7세대에 이른 지금, 그랜저는 다시 한번 진화했다. GN7이라는 코드명 아래 탄생한 이 세단은 '감각적 스포티니스'라는 새로운 디자인 철학을 담아냈다. 세계 최초로 양산차에 적용된 히든 라이트 헤드램프가 어둠 속에서 222개의 LED를 순차 점등하며 존재감을 드러낼 때, 보는 이는 미래가 이미 도착했음을 직감하게 된다.\n\n심장부에는 스마트스트림 G2.5 엔진이 자리한다. 198마력의 출력과 25.5kgf·m의 토크가 8단 자동변속기와 만나 노면 위를 미끄러지듯 나아간다. 0-100km/h 가속 9.2초. 화려하지 않지만, 그랜저가 추구하는 것은 언제나 과시가 아닌 여유였다.\n\n운전석에 앉으면 12.3인치 파노라믹 커브드 디스플레이가 시선을 사로잡는다. BOSE 12스피커 사운드 시스템이 만들어내는 640W의 음향, 64컬러 앰비언트 라이팅이 그려내는 분위기. 이곳은 단순한 운전석이 아니라 자신만의 공간이다.\n\n40년 가까이 대한민국 도로 위에서 달려온 그랜저. 누적 판매 240만 대라는 숫자가 증명하듯, 이 차는 단순한 모델명이 아니다. 세대를 관통하는 하나의 문화이자, 여전히 많은 이들이 꿈꾸는 목표다."
    },
    "image": "/images/grandeur.jpg",
    "price": "3,768만원 ~ 4,769만원"
  }
]
